LICENSE
README.md
setup.py
gamepkg/__init__.py
gamepkg/main.py
gamepkg/utils/__init__.py
gamepkg/utils/utils.py
rockgame.egg-info/PKG-INFO
rockgame.egg-info/SOURCES.txt
rockgame.egg-info/dependency_links.txt
rockgame.egg-info/entry_points.txt
rockgame.egg-info/requires.txt
rockgame.egg-info/top_level.txt