Metadata-Version: 2.1
Name: rockgame
Version: 0.1.0
Summary: Rock scissor paper game
Home-page: https://github.com/srazasuper/rock_paper_scissor_cli
Author: Syed Raza
Author-email: sraza@linuxmail.org
License: MIT
Platform: UNKNOWN
Classifier: License :: OSI Approved :: MIT License
Classifier: Programming Language :: Python
Classifier: Programming Language :: Python :: 3
Classifier: Programming Language :: Python :: 3.6
Classifier: Programming Language :: Python :: Implementation :: CPython
Classifier: Programming Language :: Python :: Implementation :: PyPy
Requires-Python: >=3.6.0
License-File: LICENSE
